{
    "version":  "0.8.1",
    "description": "Next-gen file explorer. Engineered entirely from scratch for light-speed performance, featuring a modern and robust interface.",
    "url":  "https://filepilot.nyc3.cdn.digitaloceanspaces.com/2026-07-15-v0.8.1/FPilot.exe",
    "hash": "4234cabddbf7c9e66815119d1e51424e1ef6ddac1e5ce444aea3445a26e0761f",
    "bin":  "FPilot.exe",
    "homepage": "https://filepilot.tech/",
    "shortcuts": [
        [
            "FPilot.exe",
            "fpilot"
        ]
    ]
}
